fake_memcached/__init__.py
fake_memcached/fake_memcached.py
fake_memcached-0.1.1.dist-info/LICENSE
fake_memcached-0.1.1.dist-info/METADATA
fake_memcached-0.1.1.dist-info/WHEEL
fake_memcached-0.1.1.dist-info/top_level.txt
fake_memcached-0.1.1.dist-info/RECORD
