Metadata-Version: 2.1
Name: fake-memcached
Version: 0.1.1
Summary: Dict based implementation of memcached
Home-page: https://github.com/YAtOff/fake_memcached
Author: Yavor Atov
Author-email: yavor.atov@gmail.com
License: Apache Software License 2.0
Keywords: fake_memcached
Platform: UNKNOWN
Classifier: Development Status :: 2 - Pre-Alpha
Classifier: Intended Audience :: Developers
Classifier: License :: OSI Approved :: Apache Software License
Classifier: Natural Language :: English
Classifier: Programming Language :: Python :: 3
Classifier: Programming Language :: Python :: 3.6
Classifier: Programming Language :: Python :: 3.7
Classifier: Programming Language :: Python :: 3.8
Classifier: Programming Language :: Python :: 3.9
Classifier: Programming Language :: Python :: 3.10
Requires-Python: >=3.6
License-File: LICENSE
